analyticsTestNN1/__init__.py
analyticsTestNN1/analytics.py
analyticsTestNN1/helpers.py
analyticsTestNN1-1.0.0.dist-info/LICENSE
analyticsTestNN1-1.0.0.dist-info/METADATA
analyticsTestNN1-1.0.0.dist-info/WHEEL
analyticsTestNN1-1.0.0.dist-info/top_level.txt
analyticsTestNN1-1.0.0.dist-info/RECORD
