Metadata-Version: 2.1
Name: analyticsTestNN1
Version: 1.0.0
Summary: Testing out the analytics package
Home-page: UNKNOWN
Author: Testing@testing
Author-email: UNKNOWN
License: MIT
Platform: UNKNOWN
Requires-Dist: pandas
